bcrizz/__init__.py
bcrizz-4.0.dist-info/LICENSE.txt
bcrizz-4.0.dist-info/METADATA
bcrizz-4.0.dist-info/WHEEL
bcrizz-4.0.dist-info/top_level.txt
bcrizz-4.0.dist-info/RECORD
