Metadata-Version: 2.1
Name: bcrizz
Version: 4.0
Summary: Basic desc
Home-page: UNKNOWN
Author: abc
Author-email: abc249566@gmail.com
License: UNKNOWN
Platform: UNKNOWN
Classifier: Programming Language :: Python :: 3
Classifier: License :: OSI Approved :: MIT License
Classifier: Operating System :: OS Independent
License-File: LICENSE.txt
